pywrapper/__init__.py
pywrapper/decorators.py
pywrapper/errors.py
pywrapper/handler.py
pywrapper_flask-0.1.0.dist-info/METADATA
pywrapper_flask-0.1.0.dist-info/WHEEL
pywrapper_flask-0.1.0.dist-info/top_level.txt
pywrapper_flask-0.1.0.dist-info/RECORD
