Metadata-Version: 2.1
Name: pywrapper-flask
Version: 0.1.0
Summary: Package to auto marshall and unmarshall flask requests
Home-page: https://github.com/hgromer/pywrapper
Author: Hernan Romer
Author-email: nanug33@gmail.com
License: UNKNOWN
Platform: UNKNOWN
Classifier: Programming Language :: Python :: 3
Classifier: License :: OSI Approved :: MIT License
Classifier: Operating System :: OS Independent
Requires-Python: >=3.7
